kaskara/__init__.py
kaskara/analyser.py
kaskara/analysis.py
kaskara/clang/__init__.py
kaskara/clang/analyser.py
kaskara/clang/analysis.py
kaskara/clang/backend/.dockerignore
kaskara/clang/backend/CMakeLists.txt
kaskara/clang/backend/Dockerfile
kaskara/clang/backend/cmake/FindClang.cmake
kaskara/clang/backend/cmake/FindLLVM.cmake
kaskara/clang/backend/scripts/kaskara-function-scanner
kaskara/clang/backend/scripts/kaskara-insertion-point-finder
kaskara/clang/backend/scripts/kaskara-loop-finder
kaskara/clang/backend/scripts/kaskara-snippet-extractor
kaskara/clang/backend/scripts/kaskara-statement-finder
kaskara/clang/backend/src/CMakeLists.txt
kaskara/clang/backend/src/FunctionDB.cpp
kaskara/clang/backend/src/FunctionDB.h
kaskara/clang/backend/src/InsertionPointDB.cpp
kaskara/clang/backend/src/InsertionPointDB.h
kaskara/clang/backend/src/LoopDB.cpp
kaskara/clang/backend/src/LoopDB.h
kaskara/clang/backend/src/ReadWriteAnalyzer.cpp
kaskara/clang/backend/src/ReadWriteAnalyzer.h
kaskara/clang/backend/src/SnippetDB.cpp
kaskara/clang/backend/src/SnippetDB.h
kaskara/clang/backend/src/StatementDB.cpp
kaskara/clang/backend/src/StatementDB.h
kaskara/clang/backend/src/SyntaxScopeAnalyzer.cpp
kaskara/clang/backend/src/SyntaxScopeAnalyzer.h
kaskara/clang/backend/src/function-scanner.cpp
kaskara/clang/backend/src/insertion-point-finder.cpp
kaskara/clang/backend/src/loop-finder.cpp
kaskara/clang/backend/src/main.cpp
kaskara/clang/backend/src/snippet-extractor.cpp
kaskara/clang/backend/src/statement-finder.cpp
kaskara/clang/backend/src/util.cpp
kaskara/clang/backend/src/util.h
kaskara/clang/post_install.py
kaskara/container.py
kaskara/core.py
kaskara/exceptions.py
kaskara/functions.py
kaskara/insertions.py
kaskara/loops.py
kaskara/post_install.py
kaskara/project.py
kaskara/python/__init__.py
kaskara/python/analyser.py
kaskara/python/analysis.py
kaskara/python/functions.py
kaskara/python/loops.py
kaskara/python/statements.py
kaskara/python/util.py
kaskara/spoon/__init__.py
kaskara-0.2.1.dist-info/LICENSE
kaskara-0.2.1.dist-info/METADATA
kaskara-0.2.1.dist-info/WHEEL
kaskara-0.2.1.dist-info/RECORD
