Metadata-Version: 2.1
Name: kaskara
Version: 0.2.1
Summary: A simple, unified API for various static analysers
Home-page: https://github.com/ChrisTimperley/Kaskara
License: Apache-2.0
Author: Chris Timperley
Author-email: ctimperley@cmu.edu
Requires-Python: >=3.11,<4
Classifier: Intended Audience :: Developers
Classifier: License :: OSI Approved :: Apache Software License
Classifier: Programming Language :: Python :: 3
Classifier: Programming Language :: Python :: 3.11
Classifier: Programming Language :: Python :: 3.12
Classifier: Programming Language :: Python :: 3.10
Classifier: Programming Language :: Python :: 3.9
Requires-Dist: astor (>=0.8,<0.9)
Requires-Dist: asttokens (>=2.0,<3.0)
Requires-Dist: attrs (>=19.3.0)
Requires-Dist: dockerblade (>=0.6,<0.7)
Requires-Dist: importlib_resources (>=1.0)
Requires-Dist: loguru (>=0.4.0)
Requires-Dist: requests (==2.31.0)
Requires-Dist: sourcelocation (>=1.0,<2.0)
Project-URL: Repository, https://github.com/ChrisTimperley/Kaskara
